codigo/__init__.py
codigo/code.py
calcmaster1-0.0.2.dist-info/LICENCE
calcmaster1-0.0.2.dist-info/METADATA
calcmaster1-0.0.2.dist-info/WHEEL
calcmaster1-0.0.2.dist-info/top_level.txt
calcmaster1-0.0.2.dist-info/RECORD
