Metadata-Version: 2.1
Name: calcmaster1
Version: 0.0.2
Summary: paquete calculadora basica 
Home-page: https://github.com/juliorodriguez23/proyectos
Author: juliorodriguez
Author-email: julio_rz23@hotmail.com
License: UNKNOWN
Platform: UNKNOWN
